Metadata-Version: 2.1
Name: zhyscrapy
Version: 1.0
Summary: scrapy通用爬虫
Author: zhy
Author-email: 191517137@qq.com
Requires-Python: >=3.6
